

{
    "tracks": {
      "data": [
        {
          "id": 924652282,
          "title": "Recairei (Ao Vivo)",
          "title_short": "Recairei",
          "title_version": "(Ao Vivo)",
          "link": "https://www.deezer.com/track/924652282",
          "duration": 166,
          "rank": 970618,
          "explicit_lyrics": false,
          "explicit_content_lyrics": 0,
          "explicit_content_cover": 0,
          "preview": "https://cdns-preview-7.dzcdn.net/stream/c-778ba30407d158afbb9274b4b3d9a741-5.mp3",
          "md5_image": "78505892ee23fec96a165ffd279b7f38",
          "position": 1,
          "artist": {
            "id": 61474832,
            "name": "Os Barões Da Pisadinha",
            "link": "https://www.deezer.com/artist/61474832",
            "picture": "https://api.deezer.com/artist/61474832/image",
            "picture_small": "https://cdns-images.dzcdn.net/images/artist/38f1b17eb8b5bc598109a9e4807cf392/56x56-000000-80-0-0.jpg",
            "picture_medium": "https://cdns-images.dzcdn.net/images/artist/38f1b17eb8b5bc598109a9e4807cf392/250x250-000000-80-0-0.jpg",
            "picture_big": "https://cdns-images.dzcdn.net/images/artist/38f1b17eb8b5bc598109a9e4807cf392/500x500-000000-80-0-0.jpg",
            "picture_xl": "https://cdns-images.dzcdn.net/images/artist/38f1b17eb8b5bc598109a9e4807cf392/1000x1000-000000-80-0-0.jpg",
            "radio": true,
            "tracklist": "https://api.deezer.com/artist/61474832/top?limit=50",
            "type": "artist"
          },
          "album": {
            "id": 140589232,
            "title": "Recairei (Ao Vivo)",
            "cover": "https://api.deezer.com/album/140589232/image",
            "cover_small": "https://cdns-images.dzcdn.net/images/cover/78505892ee23fec96a165ffd279b7f38/56x56-000000-80-0-0.jpg",
            "cover_medium": "https://cdns-images.dzcdn.net/images/cover/78505892ee23fec96a165ffd279b7f38/250x250-000000-80-0-0.jpg",
            "cover_big": "https://cdns-images.dzcdn.net/images/cover/78505892ee23fec96a165ffd279b7f38/500x500-000000-80-0-0.jpg",
            "cover_xl": "https://cdns-images.dzcdn.net/images/cover/78505892ee23fec96a165ffd279b7f38/1000x1000-000000-80-0-0.jpg",
            "md5_image": "78505892ee23fec96a165ffd279b7f38",
            "tracklist": "https://api.deezer.com/album/140589232/tracks",
            "type": "album"
          },
          "type": "track"
        },
        {
          "id": 966567232,
          "title": "Basta Você Me Ligar (Ao Vivo)",
          "title_short": "Basta Você Me Ligar",
          "title_version": "(Ao Vivo)",
          "link": "https://www.deezer.com/track/966567232",
          "duration": 182,
          "rank": 974386,
          "explicit_lyrics": false,
          "explicit_content_lyrics": 0,
          "explicit_content_cover": 0,
          "preview": "https://cdns-preview-f.dzcdn.net/stream/c-f0ef239584fc05afcbee249992503373-3.mp3",
          "md5_image": "b7b86fe022bff7fe15e40599ab6f5146",
          "position": 2,
          "artist": {
            "id": 61474832,
            "name": "Os Barões Da Pisadinha",
            "link": "https://www.deezer.com/artist/61474832",
            "picture": "https://api.deezer.com/artist/61474832/image",
            "picture_small": "https://cdns-images.dzcdn.net/images/artist/38f1b17eb8b5bc598109a9e4807cf392/56x56-000000-80-0-0.jpg",
            "picture_medium": "https://cdns-images.dzcdn.net/images/artist/38f1b17eb8b5bc598109a9e4807cf392/250x250-000000-80-0-0.jpg",
            "picture_big": "https://cdns-images.dzcdn.net/images/artist/38f1b17eb8b5bc598109a9e4807cf392/500x500-000000-80-0-0.jpg",
            "picture_xl": "https://cdns-images.dzcdn.net/images/artist/38f1b17eb8b5bc598109a9e4807cf392/1000x1000-000000-80-0-0.jpg",
            "radio": true,
            "tracklist": "https://api.deezer.com/artist/61474832/top?limit=50",
            "type": "artist"
          },
          "album": {
            "id": 149515222,
            "title": "Conquistas - EP 1 (Ao Vivo)",
            "cover": "https://api.deezer.com/album/149515222/image",
            "cover_small": "https://cdns-images.dzcdn.net/images/cover/b7b86fe022bff7fe15e40599ab6f5146/56x56-000000-80-0-0.jpg",
            "cover_medium": "https://cdns-images.dzcdn.net/images/cover/b7b86fe022bff7fe15e40599ab6f5146/250x250-000000-80-0-0.jpg",
            "cover_big": "https://cdns-images.dzcdn.net/images/cover/b7b86fe022bff7fe15e40599ab6f5146/500x500-000000-80-0-0.jpg",
            "cover_xl": "https://cdns-images.dzcdn.net/images/cover/b7b86fe022bff7fe15e40599ab6f5146/1000x1000-000000-80-0-0.jpg",
            "md5_image": "b7b86fe022bff7fe15e40599ab6f5146",
            "tracklist": "https://api.deezer.com/album/149515222/tracks",
            "type": "album"
          },
          "type": "track"
        },
        {
          "id": 1097130172,
          "title": "Amor ou o Litrão",
          "title_short": "Amor ou o Litrão",
          "title_version": "",
          "link": "https://www.deezer.com/track/1097130172",
          "duration": 173,
          "rank": 100000,
          "explicit_lyrics": false,
          "explicit_content_lyrics": 0,
          "explicit_content_cover": 0,
          "preview": "https://cdns-preview-f.dzcdn.net/stream/c-f7f51d56fd7ed91ee59f7092b733b30e-3.mp3",
          "md5_image": "c2e0283abe20e82fffc8beccb69ec2e1",
          "position": 3,
          "artist": {
            "id": 58559502,
            "name": "Petter Ferraz",
            "link": "https://www.deezer.com/artist/58559502",
            "picture": "https://api.deezer.com/artist/58559502/image",
            "picture_small": "https://cdns-images.dzcdn.net/images/artist/80069563bb4bc0e39d89d88444dc2f5a/56x56-000000-80-0-0.jpg",
            "picture_medium": "https://cdns-images.dzcdn.net/images/artist/80069563bb4bc0e39d89d88444dc2f5a/250x250-000000-80-0-0.jpg",
            "picture_big": "https://cdns-images.dzcdn.net/images/artist/80069563bb4bc0e39d89d88444dc2f5a/500x500-000000-80-0-0.jpg",
            "picture_xl": "https://cdns-images.dzcdn.net/images/artist/80069563bb4bc0e39d89d88444dc2f5a/1000x1000-000000-80-0-0.jpg",
            "radio": true,
            "tracklist": "https://api.deezer.com/artist/58559502/top?limit=50",
            "type": "artist"
          },
          "album": {
            "id": 177040462,
            "title": "Amor ou o Litrão",
            "cover": "https://api.deezer.com/album/177040462/image",
            "cover_small": "https://cdns-images.dzcdn.net/images/cover/c2e0283abe20e82fffc8beccb69ec2e1/56x56-000000-80-0-0.jpg",
            "cover_medium": "https://cdns-images.dzcdn.net/images/cover/c2e0283abe20e82fffc8beccb69ec2e1/250x250-000000-80-0-0.jpg",
            "cover_big": "https://cdns-images.dzcdn.net/images/cover/c2e0283abe20e82fffc8beccb69ec2e1/500x500-000000-80-0-0.jpg",
            "cover_xl": "https://cdns-images.dzcdn.net/images/cover/c2e0283abe20e82fffc8beccb69ec2e1/1000x1000-000000-80-0-0.jpg",
            "md5_image": "c2e0283abe20e82fffc8beccb69ec2e1",
            "tracklist": "https://api.deezer.com/album/177040462/tracks",
            "type": "album"
          },
          "type": "track"
        },
        {
          "id": 1125115422,
          "title": "Ele É Ele, Eu Sou Eu",
          "title_short": "Ele É Ele, Eu Sou Eu",
          "title_version": "",
          "link": "https://www.deezer.com/track/1125115422",
          "duration": 155,
          "rank": 100000,
          "explicit_lyrics": false,
          "explicit_content_lyrics": 0,
          "explicit_content_cover": 0,
          "preview": "https://cdns-preview-4.dzcdn.net/stream/c-4fb5eb191bb56f7547f3c162e3595b56-3.mp3",
          "md5_image": "d19a0b7eb0352bb5eeaad7a78fc71827",
          "position": 4,
          "artist": {
            "id": 4611283,
            "name": "Wesley Safadão",
            "link": "https://www.deezer.com/artist/4611283",
            "picture": "https://api.deezer.com/artist/4611283/image",
            "picture_small": "https://cdns-images.dzcdn.net/images/artist/d98c2a78c815e68712a0941c208bb7ba/56x56-000000-80-0-0.jpg",
            "picture_medium": "https://cdns-images.dzcdn.net/images/artist/d98c2a78c815e68712a0941c208bb7ba/250x250-000000-80-0-0.jpg",
            "picture_big": "https://cdns-images.dzcdn.net/images/artist/d98c2a78c815e68712a0941c208bb7ba/500x500-000000-80-0-0.jpg",
            "picture_xl": "https://cdns-images.dzcdn.net/images/artist/d98c2a78c815e68712a0941c208bb7ba/1000x1000-000000-80-0-0.jpg",
            "radio": true,
            "tracklist": "https://api.deezer.com/artist/4611283/top?limit=50",
            "type": "artist"
          },
          "album": {
            "id": 182865632,
            "title": "Ele É Ele, Eu Sou Eu",
            "cover": "https://api.deezer.com/album/182865632/image",
            "cover_small": "https://cdns-images.dzcdn.net/images/cover/d19a0b7eb0352bb5eeaad7a78fc71827/56x56-000000-80-0-0.jpg",
            "cover_medium": "https://cdns-images.dzcdn.net/images/cover/d19a0b7eb0352bb5eeaad7a78fc71827/250x250-000000-80-0-0.jpg",
            "cover_big": "https://cdns-images.dzcdn.net/images/cover/d19a0b7eb0352bb5eeaad7a78fc71827/500x500-000000-80-0-0.jpg",
            "cover_xl": "https://cdns-images.dzcdn.net/images/cover/d19a0b7eb0352bb5eeaad7a78fc71827/1000x1000-000000-80-0-0.jpg",
            "md5_image": "d19a0b7eb0352bb5eeaad7a78fc71827",
            "tracklist": "https://api.deezer.com/album/182865632/tracks",
            "type": "album"
          },
          "type": "track"
        },
        {
          "id": 1159617832,
          "title": "Meia Noite (Você tem meu Whatsapp)",
          "title_short": "Meia Noite (Você tem meu Whatsapp)",
          "title_version": "",
          "link": "https://www.deezer.com/track/1159617832",
          "duration": 237,
          "rank": 100000,
          "explicit_lyrics": false,
          "explicit_content_lyrics": 0,
          "explicit_content_cover": 0,
          "preview": "https://cdns-preview-a.dzcdn.net/stream/c-aa1edc45b10a07ef40a4c7a60ee15c98-3.mp3",
          "md5_image": "29daa56c5ed902ed179470b7b5ab28b7",
          "position": 5,
          "artist": {
            "id": 84292982,
            "name": "Tarcísio do Acordeon",
            "link": "https://www.deezer.com/artist/84292982",
            "picture": "https://api.deezer.com/artist/84292982/image",
            "picture_small": "https://cdns-images.dzcdn.net/images/artist/94548d0fe20cecb5346e958d4aaed9e9/56x56-000000-80-0-0.jpg",
            "picture_medium": "https://cdns-images.dzcdn.net/images/artist/94548d0fe20cecb5346e958d4aaed9e9/250x250-000000-80-0-0.jpg",
            "picture_big": "https://cdns-images.dzcdn.net/images/artist/94548d0fe20cecb5346e958d4aaed9e9/500x500-000000-80-0-0.jpg",
            "picture_xl": "https://cdns-images.dzcdn.net/images/artist/94548d0fe20cecb5346e958d4aaed9e9/1000x1000-000000-80-0-0.jpg",
            "radio": true,
            "tracklist": "https://api.deezer.com/artist/84292982/top?limit=50",
            "type": "artist"
          },
          "album": {
            "id": 189821362,
            "title": "Meia Noite (Você tem meu Whatsapp)",
            "cover": "https://api.deezer.com/album/189821362/image",
            "cover_small": "https://cdns-images.dzcdn.net/images/cover/29daa56c5ed902ed179470b7b5ab28b7/56x56-000000-80-0-0.jpg",
            "cover_medium": "https://cdns-images.dzcdn.net/images/cover/29daa56c5ed902ed179470b7b5ab28b7/250x250-000000-80-0-0.jpg",
            "cover_big": "https://cdns-images.dzcdn.net/images/cover/29daa56c5ed902ed179470b7b5ab28b7/500x500-000000-80-0-0.jpg",
            "cover_xl": "https://cdns-images.dzcdn.net/images/cover/29daa56c5ed902ed179470b7b5ab28b7/1000x1000-000000-80-0-0.jpg",
            "md5_image": "29daa56c5ed902ed179470b7b5ab28b7",
            "tracklist": "https://api.deezer.com/album/189821362/tracks",
            "type": "album"
          },
          "type": "track"
        },
        {
          "id": 1121212852,
          "title": "Letícia",
          "title_short": "Letícia",
          "title_version": "",
          "link": "https://www.deezer.com/track/1121212852",
          "duration": 167,
          "rank": 100000,
          "explicit_lyrics": false,
          "explicit_content_lyrics": 0,
          "explicit_content_cover": 0,
          "preview": "https://cdns-preview-2.dzcdn.net/stream/c-2dc4b67003d980063f54dcd5004e8551-3.mp3",
          "md5_image": "994c208e9777108feb2bce58b34bf374",
          "position": 6,
          "artist": {
            "id": 68221232,
            "name": "Zé Vaqueiro",
            "link": "https://www.deezer.com/artist/68221232",
            "picture": "https://api.deezer.com/artist/68221232/image",
            "picture_small": "https://cdns-images.dzcdn.net/images/artist/d7a7aa96042e571ad1de55ddd20831bf/56x56-000000-80-0-0.jpg",
            "picture_medium": "https://cdns-images.dzcdn.net/images/artist/d7a7aa96042e571ad1de55ddd20831bf/250x250-000000-80-0-0.jpg",
            "picture_big": "https://cdns-images.dzcdn.net/images/artist/d7a7aa96042e571ad1de55ddd20831bf/500x500-000000-80-0-0.jpg",
            "picture_xl": "https://cdns-images.dzcdn.net/images/artist/d7a7aa96042e571ad1de55ddd20831bf/1000x1000-000000-80-0-0.jpg",
            "radio": true,
            "tracklist": "https://api.deezer.com/artist/68221232/top?limit=50",
            "type": "artist"
          },
          "album": {
            "id": 182102482,
            "title": "O Original",
            "cover": "https://api.deezer.com/album/182102482/image",
            "cover_small": "https://cdns-images.dzcdn.net/images/cover/994c208e9777108feb2bce58b34bf374/56x56-000000-80-0-0.jpg",
            "cover_medium": "https://cdns-images.dzcdn.net/images/cover/994c208e9777108feb2bce58b34bf374/250x250-000000-80-0-0.jpg",
            "cover_big": "https://cdns-images.dzcdn.net/images/cover/994c208e9777108feb2bce58b34bf374/500x500-000000-80-0-0.jpg",
            "cover_xl": "https://cdns-images.dzcdn.net/images/cover/994c208e9777108feb2bce58b34bf374/1000x1000-000000-80-0-0.jpg",
            "md5_image": "994c208e9777108feb2bce58b34bf374",
            "tracklist": "https://api.deezer.com/album/182102482/tracks",
            "type": "album"
          },
          "type": "track"
        },
        {
          "id": 763124462,
          "title": "Tá Rocheda",
          "title_short": "Tá Rocheda",
          "title_version": "",
          "link": "https://www.deezer.com/track/763124462",
          "duration": 203,
          "rank": 960146,
          "explicit_lyrics": false,
          "explicit_content_lyrics": 0,
          "explicit_content_cover": 0,
          "preview": "https://cdns-preview-6.dzcdn.net/stream/c-69b83a0b48b4deba70363a6de54f0e74-5.mp3",
          "md5_image": "aba8b6e34742af2214644f31e136789f",
          "position": 7,
          "artist": {
            "id": 61474832,
            "name": "Os Barões Da Pisadinha",
            "link": "https://www.deezer.com/artist/61474832",
            "picture": "https://api.deezer.com/artist/61474832/image",
            "picture_small": "https://cdns-images.dzcdn.net/images/artist/38f1b17eb8b5bc598109a9e4807cf392/56x56-000000-80-0-0.jpg",
            "picture_medium": "https://cdns-images.dzcdn.net/images/artist/38f1b17eb8b5bc598109a9e4807cf392/250x250-000000-80-0-0.jpg",
            "picture_big": "https://cdns-images.dzcdn.net/images/artist/38f1b17eb8b5bc598109a9e4807cf392/500x500-000000-80-0-0.jpg",
            "picture_xl": "https://cdns-images.dzcdn.net/images/artist/38f1b17eb8b5bc598109a9e4807cf392/1000x1000-000000-80-0-0.jpg",
            "radio": true,
            "tracklist": "https://api.deezer.com/artist/61474832/top?limit=50",
            "type": "artist"
          },
          "album": {
            "id": 112625202,
            "title": "As Melhores 2018",
            "cover": "https://api.deezer.com/album/112625202/image",
            "cover_small": "https://cdns-images.dzcdn.net/images/cover/aba8b6e34742af2214644f31e136789f/56x56-000000-80-0-0.jpg",
            "cover_medium": "https://cdns-images.dzcdn.net/images/cover/aba8b6e34742af2214644f31e136789f/250x250-000000-80-0-0.jpg",
            "cover_big": "https://cdns-images.dzcdn.net/images/cover/aba8b6e34742af2214644f31e136789f/500x500-000000-80-0-0.jpg",
            "cover_xl": "https://cdns-images.dzcdn.net/images/cover/aba8b6e34742af2214644f31e136789f/1000x1000-000000-80-0-0.jpg",
            "md5_image": "aba8b6e34742af2214644f31e136789f",
            "tracklist": "https://api.deezer.com/album/112625202/tracks",
            "type": "album"
          },
          "type": "track"
        },
        {
          "id": 1018572432,
          "title": "Rita",
          "title_short": "Rita",
          "title_version": "",
          "link": "https://www.deezer.com/track/1018572432",
          "duration": 156,
          "rank": 658770,
          "explicit_lyrics": false,
          "explicit_content_lyrics": 0,
          "explicit_content_cover": 0,
          "preview": "https://cdns-preview-d.dzcdn.net/stream/c-dd13a0c1f5f211537b647a1e40d8ea37-3.mp3",
          "md5_image": "75682eaa09c8416225446d151644cd86",
          "position": 8,
          "artist": {
            "id": 3126151,
            "name": "Tierry",
            "link": "https://www.deezer.com/artist/3126151",
            "picture": "https://api.deezer.com/artist/3126151/image",
            "picture_small": "https://cdns-images.dzcdn.net/images/artist/20fea2cc755f9ab809294ddfff427043/56x56-000000-80-0-0.jpg",
            "picture_medium": "https://cdns-images.dzcdn.net/images/artist/20fea2cc755f9ab809294ddfff427043/250x250-000000-80-0-0.jpg",
            "picture_big": "https://cdns-images.dzcdn.net/images/artist/20fea2cc755f9ab809294ddfff427043/500x500-000000-80-0-0.jpg",
            "picture_xl": "https://cdns-images.dzcdn.net/images/artist/20fea2cc755f9ab809294ddfff427043/1000x1000-000000-80-0-0.jpg",
            "radio": true,
            "tracklist": "https://api.deezer.com/artist/3126151/top?limit=50",
            "type": "artist"
          },
          "album": {
            "id": 160206182,
            "title": "Aô Saudade da Mãe dos Meninos",
            "cover": "https://api.deezer.com/album/160206182/image",
            "cover_small": "https://cdns-images.dzcdn.net/images/cover/75682eaa09c8416225446d151644cd86/56x56-000000-80-0-0.jpg",
            "cover_medium": "https://cdns-images.dzcdn.net/images/cover/75682eaa09c8416225446d151644cd86/250x250-000000-80-0-0.jpg",
            "cover_big": "https://cdns-images.dzcdn.net/images/cover/75682eaa09c8416225446d151644cd86/500x500-000000-80-0-0.jpg",
            "cover_xl": "https://cdns-images.dzcdn.net/images/cover/75682eaa09c8416225446d151644cd86/1000x1000-000000-80-0-0.jpg",
            "md5_image": "75682eaa09c8416225446d151644cd86",
            "tracklist": "https://api.deezer.com/album/160206182/tracks",
            "type": "album"
          },
          "type": "track"
        },
        {
          "id": 1015198102,
          "title": "Casa de Praia (Ao Vivo)",
          "title_short": "Casa de Praia",
          "title_version": "(Ao Vivo)",
          "link": "https://www.deezer.com/track/1015198102",
          "duration": 146,
          "rank": 869537,
          "explicit_lyrics": false,
          "explicit_content_lyrics": 0,
          "explicit_content_cover": 0,
          "preview": "https://cdns-preview-b.dzcdn.net/stream/c-b8c15d845db630da2e403688086e15fe-3.mp3",
          "md5_image": "f7f6e7c5795715b4a76131566251a356",
          "position": 9,
          "artist": {
            "id": 61474832,
            "name": "Os Barões Da Pisadinha",
            "link": "https://www.deezer.com/artist/61474832",
            "picture": "https://api.deezer.com/artist/61474832/image",
            "picture_small": "https://cdns-images.dzcdn.net/images/artist/38f1b17eb8b5bc598109a9e4807cf392/56x56-000000-80-0-0.jpg",
            "picture_medium": "https://cdns-images.dzcdn.net/images/artist/38f1b17eb8b5bc598109a9e4807cf392/250x250-000000-80-0-0.jpg",
            "picture_big": "https://cdns-images.dzcdn.net/images/artist/38f1b17eb8b5bc598109a9e4807cf392/500x500-000000-80-0-0.jpg",
            "picture_xl": "https://cdns-images.dzcdn.net/images/artist/38f1b17eb8b5bc598109a9e4807cf392/1000x1000-000000-80-0-0.jpg",
            "radio": true,
            "tracklist": "https://api.deezer.com/artist/61474832/top?limit=50",
            "type": "artist"
          },
          "album": {
            "id": 159392982,
            "title": "Conquistas - EP 3 (Ao Vivo)",
            "cover": "https://api.deezer.com/album/159392982/image",
            "cover_small": "https://cdns-images.dzcdn.net/images/cover/f7f6e7c5795715b4a76131566251a356/56x56-000000-80-0-0.jpg",
            "cover_medium": "https://cdns-images.dzcdn.net/images/cover/f7f6e7c5795715b4a76131566251a356/250x250-000000-80-0-0.jpg",
            "cover_big": "https://cdns-images.dzcdn.net/images/cover/f7f6e7c5795715b4a76131566251a356/500x500-000000-80-0-0.jpg",
            "cover_xl": "https://cdns-images.dzcdn.net/images/cover/f7f6e7c5795715b4a76131566251a356/1000x1000-000000-80-0-0.jpg",
            "md5_image": "f7f6e7c5795715b4a76131566251a356",
            "tracklist": "https://api.deezer.com/album/159392982/tracks",
            "type": "album"
          },
          "type": "track"
        },
        {
          "id": 980264672,
          "title": "Figurinha (Ao Vivo)",
          "title_short": "Figurinha",
          "title_version": "(Ao Vivo)",
          "link": "https://www.deezer.com/track/980264672",
          "duration": 206,
          "rank": 957985,
          "explicit_lyrics": false,
          "explicit_content_lyrics": 0,
          "explicit_content_cover": 0,
          "preview": "https://cdns-preview-5.dzcdn.net/stream/c-5008e967c5fab8ebdb475ab57eff0a68-3.mp3",
          "md5_image": "f298d32189227ffbbf6607a0318ae917",
          "position": 10,
          "artist": {
            "id": 12383494,
            "name": "Douglas & Vinicius",
            "link": "https://www.deezer.com/artist/12383494",
            "picture": "https://api.deezer.com/artist/12383494/image",
            "picture_small": "https://cdns-images.dzcdn.net/images/artist/a5186c3936df2062568367442e49a440/56x56-000000-80-0-0.jpg",
            "picture_medium": "https://cdns-images.dzcdn.net/images/artist/a5186c3936df2062568367442e49a440/250x250-000000-80-0-0.jpg",
            "picture_big": "https://cdns-images.dzcdn.net/images/artist/a5186c3936df2062568367442e49a440/500x500-000000-80-0-0.jpg",
            "picture_xl": "https://cdns-images.dzcdn.net/images/artist/a5186c3936df2062568367442e49a440/1000x1000-000000-80-0-0.jpg",
            "radio": true,
            "tracklist": "https://api.deezer.com/artist/12383494/top?limit=50",
            "type": "artist"
          },
          "album": {
            "id": 152486382,
            "title": "Figurinha (Ao Vivo)",
            "cover": "https://api.deezer.com/album/152486382/image",
            "cover_small": "https://cdns-images.dzcdn.net/images/cover/f298d32189227ffbbf6607a0318ae917/56x56-000000-80-0-0.jpg",
            "cover_medium": "https://cdns-images.dzcdn.net/images/cover/f298d32189227ffbbf6607a0318ae917/250x250-000000-80-0-0.jpg",
            "cover_big": "https://cdns-images.dzcdn.net/images/cover/f298d32189227ffbbf6607a0318ae917/500x500-000000-80-0-0.jpg",
            "cover_xl": "https://cdns-images.dzcdn.net/images/cover/f298d32189227ffbbf6607a0318ae917/1000x1000-000000-80-0-0.jpg",
            "md5_image": "f298d32189227ffbbf6607a0318ae917",
            "tracklist": "https://api.deezer.com/album/152486382/tracks",
            "type": "album"
          },
          "type": "track"
        }
      ],
      "total": 10
    },
    "albums": {
      "data": [
        {
          "id": 192564652,
          "title": "COR",
          "link": "https://www.deezer.com/album/192564652",
          "cover": "https://api.deezer.com/album/192564652/image",
          "cover_small": "https://cdns-images.dzcdn.net/images/cover/33934d8f5bfcb73b69986aa019d4ebe2/56x56-000000-80-0-0.jpg",
          "cover_medium": "https://cdns-images.dzcdn.net/images/cover/33934d8f5bfcb73b69986aa019d4ebe2/250x250-000000-80-0-0.jpg",
          "cover_big": "https://cdns-images.dzcdn.net/images/cover/33934d8f5bfcb73b69986aa019d4ebe2/500x500-000000-80-0-0.jpg",
          "cover_xl": "https://cdns-images.dzcdn.net/images/cover/33934d8f5bfcb73b69986aa019d4ebe2/1000x1000-000000-80-0-0.jpg",
          "md5_image": "33934d8f5bfcb73b69986aa019d4ebe2",
          "record_type": "album",
          "tracklist": "https://api.deezer.com/album/192564652/tracks",
          "explicit_lyrics": false,
          "position": 1,
          "artist": {
            "id": 7765128,
            "name": "ANAVITÓRIA",
            "link": "https://www.deezer.com/artist/7765128",
            "picture": "https://api.deezer.com/artist/7765128/image",
            "picture_small": "https://cdns-images.dzcdn.net/images/artist/e1521f93087aaefeabf9638fe2a14eae/56x56-000000-80-0-0.jpg",
            "picture_medium": "https://cdns-images.dzcdn.net/images/artist/e1521f93087aaefeabf9638fe2a14eae/250x250-000000-80-0-0.jpg",
            "picture_big": "https://cdns-images.dzcdn.net/images/artist/e1521f93087aaefeabf9638fe2a14eae/500x500-000000-80-0-0.jpg",
            "picture_xl": "https://cdns-images.dzcdn.net/images/artist/e1521f93087aaefeabf9638fe2a14eae/1000x1000-000000-80-0-0.jpg",
            "radio": true,
            "tracklist": "https://api.deezer.com/artist/7765128/top?limit=50",
            "type": "artist"
          },
          "type": "album"
        },
        {
          "id": 192394462,
          "title": "Diferente dos Iguais",
          "link": "https://www.deezer.com/album/192394462",
          "cover": "https://api.deezer.com/album/192394462/image",
          "cover_small": "https://cdns-images.dzcdn.net/images/cover/2669cd131c0eb27601887436aa00d8a6/56x56-000000-80-0-0.jpg",
          "cover_medium": "https://cdns-images.dzcdn.net/images/cover/2669cd131c0eb27601887436aa00d8a6/250x250-000000-80-0-0.jpg",
          "cover_big": "https://cdns-images.dzcdn.net/images/cover/2669cd131c0eb27601887436aa00d8a6/500x500-000000-80-0-0.jpg",
          "cover_xl": "https://cdns-images.dzcdn.net/images/cover/2669cd131c0eb27601887436aa00d8a6/1000x1000-000000-80-0-0.jpg",
          "md5_image": "2669cd131c0eb27601887436aa00d8a6",
          "record_type": "album",
          "tracklist": "https://api.deezer.com/album/192394462/tracks",
          "explicit_lyrics": false,
          "position": 2,
          "artist": {
            "id": 84292982,
            "name": "Tarcísio do Acordeon",
            "link": "https://www.deezer.com/artist/84292982",
            "picture": "https://api.deezer.com/artist/84292982/image",
            "picture_small": "https://cdns-images.dzcdn.net/images/artist/94548d0fe20cecb5346e958d4aaed9e9/56x56-000000-80-0-0.jpg",
            "picture_medium": "https://cdns-images.dzcdn.net/images/artist/94548d0fe20cecb5346e958d4aaed9e9/250x250-000000-80-0-0.jpg",
            "picture_big": "https://cdns-images.dzcdn.net/images/artist/94548d0fe20cecb5346e958d4aaed9e9/500x500-000000-80-0-0.jpg",
            "picture_xl": "https://cdns-images.dzcdn.net/images/artist/94548d0fe20cecb5346e958d4aaed9e9/1000x1000-000000-80-0-0.jpg",
            "radio": true,
            "tracklist": "https://api.deezer.com/artist/84292982/top?limit=50",
            "type": "artist"
          },
          "type": "album"
        },
        {
          "id": 177218102,
          "title": "Tardezinha No Maraca (Ao Vivo)",
          "link": "https://www.deezer.com/album/177218102",
          "cover": "https://api.deezer.com/album/177218102/image",
          "cover_small": "https://cdns-images.dzcdn.net/images/cover/f8c5a16701271a701ec837c047c1fa5e/56x56-000000-80-0-0.jpg",
          "cover_medium": "https://cdns-images.dzcdn.net/images/cover/f8c5a16701271a701ec837c047c1fa5e/250x250-000000-80-0-0.jpg",
          "cover_big": "https://cdns-images.dzcdn.net/images/cover/f8c5a16701271a701ec837c047c1fa5e/500x500-000000-80-0-0.jpg",
          "cover_xl": "https://cdns-images.dzcdn.net/images/cover/f8c5a16701271a701ec837c047c1fa5e/1000x1000-000000-80-0-0.jpg",
          "md5_image": "f8c5a16701271a701ec837c047c1fa5e",
          "record_type": "album",
          "tracklist": "https://api.deezer.com/album/177218102/tracks",
          "explicit_lyrics": false,
          "position": 3,
          "artist": {
            "id": 1644275,
            "name": "Thiaguinho",
            "link": "https://www.deezer.com/artist/1644275",
            "picture": "https://api.deezer.com/artist/1644275/image",
            "picture_small": "https://cdns-images.dzcdn.net/images/artist/c760d4ba6ebe2c193b0a49562874a0b5/56x56-000000-80-0-0.jpg",
            "picture_medium": "https://cdns-images.dzcdn.net/images/artist/c760d4ba6ebe2c193b0a49562874a0b5/250x250-000000-80-0-0.jpg",
            "picture_big": "https://cdns-images.dzcdn.net/images/artist/c760d4ba6ebe2c193b0a49562874a0b5/500x500-000000-80-0-0.jpg",
            "picture_xl": "https://cdns-images.dzcdn.net/images/artist/c760d4ba6ebe2c193b0a49562874a0b5/1000x1000-000000-80-0-0.jpg",
            "radio": true,
            "tracklist": "https://api.deezer.com/artist/1644275/top?limit=50",
            "type": "artist"
          },
          "type": "album"
        },
        {
          "id": 191987972,
          "title": "Os Barões da Pisadinha & Xand Avião (Ao Vivo)",
          "link": "https://www.deezer.com/album/191987972",
          "cover": "https://api.deezer.com/album/191987972/image",
          "cover_small": "https://cdns-images.dzcdn.net/images/cover/b04c0fc8cf91de93c3439c1256e22254/56x56-000000-80-0-0.jpg",
          "cover_medium": "https://cdns-images.dzcdn.net/images/cover/b04c0fc8cf91de93c3439c1256e22254/250x250-000000-80-0-0.jpg",
          "cover_big": "https://cdns-images.dzcdn.net/images/cover/b04c0fc8cf91de93c3439c1256e22254/500x500-000000-80-0-0.jpg",
          "cover_xl": "https://cdns-images.dzcdn.net/images/cover/b04c0fc8cf91de93c3439c1256e22254/1000x1000-000000-80-0-0.jpg",
          "md5_image": "b04c0fc8cf91de93c3439c1256e22254",
          "record_type": "single",
          "tracklist": "https://api.deezer.com/album/191987972/tracks",
          "explicit_lyrics": false,
          "position": 4,
          "artist": {
            "id": 61474832,
            "name": "Os Barões Da Pisadinha",
            "link": "https://www.deezer.com/artist/61474832",
            "picture": "https://api.deezer.com/artist/61474832/image",
            "picture_small": "https://cdns-images.dzcdn.net/images/artist/38f1b17eb8b5bc598109a9e4807cf392/56x56-000000-80-0-0.jpg",
            "picture_medium": "https://cdns-images.dzcdn.net/images/artist/38f1b17eb8b5bc598109a9e4807cf392/250x250-000000-80-0-0.jpg",
            "picture_big": "https://cdns-images.dzcdn.net/images/artist/38f1b17eb8b5bc598109a9e4807cf392/500x500-000000-80-0-0.jpg",
            "picture_xl": "https://cdns-images.dzcdn.net/images/artist/38f1b17eb8b5bc598109a9e4807cf392/1000x1000-000000-80-0-0.jpg",
            "radio": true,
            "tracklist": "https://api.deezer.com/artist/61474832/top?limit=50",
            "type": "artist"
          },
          "type": "album"
        },
        {
          "id": 178213952,
          "title": "Piseiro 2020 Ao Vivo",
          "link": "https://www.deezer.com/album/178213952",
          "cover": "https://api.deezer.com/album/178213952/image",
          "cover_small": "https://cdns-images.dzcdn.net/images/cover/3942d899bea9d78d9a6c1d132ba7bf00/56x56-000000-80-0-0.jpg",
          "cover_medium": "https://cdns-images.dzcdn.net/images/cover/3942d899bea9d78d9a6c1d132ba7bf00/250x250-000000-80-0-0.jpg",
          "cover_big": "https://cdns-images.dzcdn.net/images/cover/3942d899bea9d78d9a6c1d132ba7bf00/500x500-000000-80-0-0.jpg",
          "cover_xl": "https://cdns-images.dzcdn.net/images/cover/3942d899bea9d78d9a6c1d132ba7bf00/1000x1000-000000-80-0-0.jpg",
          "md5_image": "3942d899bea9d78d9a6c1d132ba7bf00",
          "record_type": "album",
          "tracklist": "https://api.deezer.com/album/178213952/tracks",
          "explicit_lyrics": false,
          "position": 5,
          "artist": {
            "id": 61474832,
            "name": "Os Barões Da Pisadinha",
            "link": "https://www.deezer.com/artist/61474832",
            "picture": "https://api.deezer.com/artist/61474832/image",
            "picture_small": "https://cdns-images.dzcdn.net/images/artist/38f1b17eb8b5bc598109a9e4807cf392/56x56-000000-80-0-0.jpg",
            "picture_medium": "https://cdns-images.dzcdn.net/images/artist/38f1b17eb8b5bc598109a9e4807cf392/250x250-000000-80-0-0.jpg",
            "picture_big": "https://cdns-images.dzcdn.net/images/artist/38f1b17eb8b5bc598109a9e4807cf392/500x500-000000-80-0-0.jpg",
            "picture_xl": "https://cdns-images.dzcdn.net/images/artist/38f1b17eb8b5bc598109a9e4807cf392/1000x1000-000000-80-0-0.jpg",
            "radio": true,
            "tracklist": "https://api.deezer.com/artist/61474832/top?limit=50",
            "type": "artist"
          },
          "type": "album"
        },
        {
          "id": 182623352,
          "title": "Churrasquinho Menos É Mais (Ao Vivo)",
          "link": "https://www.deezer.com/album/182623352",
          "cover": "https://api.deezer.com/album/182623352/image",
          "cover_small": "https://cdns-images.dzcdn.net/images/cover/9af04883c8820e30574859932b3d615d/56x56-000000-80-0-0.jpg",
          "cover_medium": "https://cdns-images.dzcdn.net/images/cover/9af04883c8820e30574859932b3d615d/250x250-000000-80-0-0.jpg",
          "cover_big": "https://cdns-images.dzcdn.net/images/cover/9af04883c8820e30574859932b3d615d/500x500-000000-80-0-0.jpg",
          "cover_xl": "https://cdns-images.dzcdn.net/images/cover/9af04883c8820e30574859932b3d615d/1000x1000-000000-80-0-0.jpg",
          "md5_image": "9af04883c8820e30574859932b3d615d",
          "record_type": "album",
          "tracklist": "https://api.deezer.com/album/182623352/tracks",
          "explicit_lyrics": false,
          "position": 6,
          "artist": {
            "id": 54330242,
            "name": "Grupo Menos É Mais",
            "link": "https://www.deezer.com/artist/54330242",
            "picture": "https://api.deezer.com/artist/54330242/image",
            "picture_small": "https://cdns-images.dzcdn.net/images/artist/738abca3b6502aa093e5df1df1dad704/56x56-000000-80-0-0.jpg",
            "picture_medium": "https://cdns-images.dzcdn.net/images/artist/738abca3b6502aa093e5df1df1dad704/250x250-000000-80-0-0.jpg",
            "picture_big": "https://cdns-images.dzcdn.net/images/artist/738abca3b6502aa093e5df1df1dad704/500x500-000000-80-0-0.jpg",
            "picture_xl": "https://cdns-images.dzcdn.net/images/artist/738abca3b6502aa093e5df1df1dad704/1000x1000-000000-80-0-0.jpg",
            "radio": true,
            "tracklist": "https://api.deezer.com/artist/54330242/top?limit=50",
            "type": "artist"
          },
          "type": "album"
        },
        {
          "id": 182102482,
          "title": "O Original",
          "link": "https://www.deezer.com/album/182102482",
          "cover": "https://api.deezer.com/album/182102482/image",
          "cover_small": "https://cdns-images.dzcdn.net/images/cover/994c208e9777108feb2bce58b34bf374/56x56-000000-80-0-0.jpg",
          "cover_medium": "https://cdns-images.dzcdn.net/images/cover/994c208e9777108feb2bce58b34bf374/250x250-000000-80-0-0.jpg",
          "cover_big": "https://cdns-images.dzcdn.net/images/cover/994c208e9777108feb2bce58b34bf374/500x500-000000-80-0-0.jpg",
          "cover_xl": "https://cdns-images.dzcdn.net/images/cover/994c208e9777108feb2bce58b34bf374/1000x1000-000000-80-0-0.jpg",
          "md5_image": "994c208e9777108feb2bce58b34bf374",
          "record_type": "album",
          "tracklist": "https://api.deezer.com/album/182102482/tracks",
          "explicit_lyrics": false,
          "position": 7,
          "artist": {
            "id": 68221232,
            "name": "Zé Vaqueiro",
            "link": "https://www.deezer.com/artist/68221232",
            "picture": "https://api.deezer.com/artist/68221232/image",
            "picture_small": "https://cdns-images.dzcdn.net/images/artist/d7a7aa96042e571ad1de55ddd20831bf/56x56-000000-80-0-0.jpg",
            "picture_medium": "https://cdns-images.dzcdn.net/images/artist/d7a7aa96042e571ad1de55ddd20831bf/250x250-000000-80-0-0.jpg",
            "picture_big": "https://cdns-images.dzcdn.net/images/artist/d7a7aa96042e571ad1de55ddd20831bf/500x500-000000-80-0-0.jpg",
            "picture_xl": "https://cdns-images.dzcdn.net/images/artist/d7a7aa96042e571ad1de55ddd20831bf/1000x1000-000000-80-0-0.jpg",
            "radio": true,
            "tracklist": "https://api.deezer.com/artist/68221232/top?limit=50",
            "type": "artist"
          },
          "type": "album"
        },
        {
          "id": 139352012,
          "title": "Melhores Os Barões da Pisadinha",
          "link": "https://www.deezer.com/album/139352012",
          "cover": "https://api.deezer.com/album/139352012/image",
          "cover_small": "https://cdns-images.dzcdn.net/images/cover/16aae97fb56a81bdfa8b46f7acc12870/56x56-000000-80-0-0.jpg",
          "cover_medium": "https://cdns-images.dzcdn.net/images/cover/16aae97fb56a81bdfa8b46f7acc12870/250x250-000000-80-0-0.jpg",
          "cover_big": "https://cdns-images.dzcdn.net/images/cover/16aae97fb56a81bdfa8b46f7acc12870/500x500-000000-80-0-0.jpg",
          "cover_xl": "https://cdns-images.dzcdn.net/images/cover/16aae97fb56a81bdfa8b46f7acc12870/1000x1000-000000-80-0-0.jpg",
          "md5_image": "16aae97fb56a81bdfa8b46f7acc12870",
          "record_type": "album",
          "tracklist": "https://api.deezer.com/album/139352012/tracks",
          "explicit_lyrics": false,
          "position": 8,
          "artist": {
            "id": 61474832,
            "name": "Os Barões Da Pisadinha",
            "link": "https://www.deezer.com/artist/61474832",
            "picture": "https://api.deezer.com/artist/61474832/image",
            "picture_small": "https://cdns-images.dzcdn.net/images/artist/38f1b17eb8b5bc598109a9e4807cf392/56x56-000000-80-0-0.jpg",
            "picture_medium": "https://cdns-images.dzcdn.net/images/artist/38f1b17eb8b5bc598109a9e4807cf392/250x250-000000-80-0-0.jpg",
            "picture_big": "https://cdns-images.dzcdn.net/images/artist/38f1b17eb8b5bc598109a9e4807cf392/500x500-000000-80-0-0.jpg",
            "picture_xl": "https://cdns-images.dzcdn.net/images/artist/38f1b17eb8b5bc598109a9e4807cf392/1000x1000-000000-80-0-0.jpg",
            "radio": true,
            "tracklist": "https://api.deezer.com/artist/61474832/top?limit=50",
            "type": "artist"
          },
          "type": "album"
        },
        {
          "id": 193572582,
          "title": "Xand Avião 2021",
          "link": "https://www.deezer.com/album/193572582",
          "cover": "https://api.deezer.com/album/193572582/image",
          "cover_small": "https://cdns-images.dzcdn.net/images/cover/cb48df0fe030c7592bd2ccc7a76a42f7/56x56-000000-80-0-0.jpg",
          "cover_medium": "https://cdns-images.dzcdn.net/images/cover/cb48df0fe030c7592bd2ccc7a76a42f7/250x250-000000-80-0-0.jpg",
          "cover_big": "https://cdns-images.dzcdn.net/images/cover/cb48df0fe030c7592bd2ccc7a76a42f7/500x500-000000-80-0-0.jpg",
          "cover_xl": "https://cdns-images.dzcdn.net/images/cover/cb48df0fe030c7592bd2ccc7a76a42f7/1000x1000-000000-80-0-0.jpg",
          "md5_image": "cb48df0fe030c7592bd2ccc7a76a42f7",
          "record_type": "album",
          "tracklist": "https://api.deezer.com/album/193572582/tracks",
          "explicit_lyrics": false,
          "position": 9,
          "artist": {
            "id": 5832280,
            "name": "Xand Avião",
            "link": "https://www.deezer.com/artist/5832280",
            "picture": "https://api.deezer.com/artist/5832280/image",
            "picture_small": "https://cdns-images.dzcdn.net/images/artist/606fbb66632064bd9138efb16c44ffed/56x56-000000-80-0-0.jpg",
            "picture_medium": "https://cdns-images.dzcdn.net/images/artist/606fbb66632064bd9138efb16c44ffed/250x250-000000-80-0-0.jpg",
            "picture_big": "https://cdns-images.dzcdn.net/images/artist/606fbb66632064bd9138efb16c44ffed/500x500-000000-80-0-0.jpg",
            "picture_xl": "https://cdns-images.dzcdn.net/images/artist/606fbb66632064bd9138efb16c44ffed/1000x1000-000000-80-0-0.jpg",
            "radio": true,
            "tracklist": "https://api.deezer.com/artist/5832280/top?limit=50",
            "type": "artist"
          },
          "type": "album"
        },
        {
          "id": 127653802,
          "title": "Sertanejo Universitário As Melhores",
          "link": "https://www.deezer.com/album/127653802",
          "cover": "https://api.deezer.com/album/127653802/image",
          "cover_small": "https://cdns-images.dzcdn.net/images/cover/d3ed037e3357edb46a26068c221d4ce1/56x56-000000-80-0-0.jpg",
          "cover_medium": "https://cdns-images.dzcdn.net/images/cover/d3ed037e3357edb46a26068c221d4ce1/250x250-000000-80-0-0.jpg",
          "cover_big": "https://cdns-images.dzcdn.net/images/cover/d3ed037e3357edb46a26068c221d4ce1/500x500-000000-80-0-0.jpg",
          "cover_xl": "https://cdns-images.dzcdn.net/images/cover/d3ed037e3357edb46a26068c221d4ce1/1000x1000-000000-80-0-0.jpg",
          "md5_image": "d3ed037e3357edb46a26068c221d4ce1",
          "record_type": "compile",
          "tracklist": "https://api.deezer.com/album/127653802/tracks",
          "explicit_lyrics": false,
          "position": 10,
          "artist": {
            "id": 5080,
            "name": "Various Artists",
            "link": "https://www.deezer.com/artist/5080",
            "picture": "https://api.deezer.com/artist/5080/image",
            "picture_small": "https://cdns-images.dzcdn.net/images/artist/6fd017dac44f23dd3e15d512e3a5d970/56x56-000000-80-0-0.jpg",
            "picture_medium": "https://cdns-images.dzcdn.net/images/artist/6fd017dac44f23dd3e15d512e3a5d970/250x250-000000-80-0-0.jpg",
            "picture_big": "https://cdns-images.dzcdn.net/images/artist/6fd017dac44f23dd3e15d512e3a5d970/500x500-000000-80-0-0.jpg",
            "picture_xl": "https://cdns-images.dzcdn.net/images/artist/6fd017dac44f23dd3e15d512e3a5d970/1000x1000-000000-80-0-0.jpg",
            "radio": false,
            "tracklist": "https://api.deezer.com/artist/5080/top?limit=50",
            "type": "artist"
          },
          "type": "album"
        }
      ],
      "total": 10
    },
    "artists": {
      "data": [
        {
          "id": 61474832,
          "name": "Os Barões Da Pisadinha",
          "link": "https://www.deezer.com/artist/61474832",
          "picture": "https://api.deezer.com/artist/61474832/image",
          "picture_small": "https://cdns-images.dzcdn.net/images/artist/38f1b17eb8b5bc598109a9e4807cf392/56x56-000000-80-0-0.jpg",
          "picture_medium": "https://cdns-images.dzcdn.net/images/artist/38f1b17eb8b5bc598109a9e4807cf392/250x250-000000-80-0-0.jpg",
          "picture_big": "https://cdns-images.dzcdn.net/images/artist/38f1b17eb8b5bc598109a9e4807cf392/500x500-000000-80-0-0.jpg",
          "picture_xl": "https://cdns-images.dzcdn.net/images/artist/38f1b17eb8b5bc598109a9e4807cf392/1000x1000-000000-80-0-0.jpg",
          "radio": true,
          "tracklist": "https://api.deezer.com/artist/61474832/top?limit=50",
          "position": 1,
          "type": "artist"
        },
        {
          "id": 1541592,
          "name": "Gusttavo Lima",
          "link": "https://www.deezer.com/artist/1541592",
          "picture": "https://api.deezer.com/artist/1541592/image",
          "picture_small": "https://cdns-images.dzcdn.net/images/artist/e89f6fd2240bf17bd155a07881fe19f3/56x56-000000-80-0-0.jpg",
          "picture_medium": "https://cdns-images.dzcdn.net/images/artist/e89f6fd2240bf17bd155a07881fe19f3/250x250-000000-80-0-0.jpg",
          "picture_big": "https://cdns-images.dzcdn.net/images/artist/e89f6fd2240bf17bd155a07881fe19f3/500x500-000000-80-0-0.jpg",
          "picture_xl": "https://cdns-images.dzcdn.net/images/artist/e89f6fd2240bf17bd155a07881fe19f3/1000x1000-000000-80-0-0.jpg",
          "radio": true,
          "tracklist": "https://api.deezer.com/artist/1541592/top?limit=50",
          "position": 2,
          "type": "artist"
        },
        {
          "id": 7068771,
          "name": "Marília Mendonça",
          "link": "https://www.deezer.com/artist/7068771",
          "picture": "https://api.deezer.com/artist/7068771/image",
          "picture_small": "https://cdns-images.dzcdn.net/images/artist/0e2f0b185fa2eef93a490f40d13d269f/56x56-000000-80-0-0.jpg",
          "picture_medium": "https://cdns-images.dzcdn.net/images/artist/0e2f0b185fa2eef93a490f40d13d269f/250x250-000000-80-0-0.jpg",
          "picture_big": "https://cdns-images.dzcdn.net/images/artist/0e2f0b185fa2eef93a490f40d13d269f/500x500-000000-80-0-0.jpg",
          "picture_xl": "https://cdns-images.dzcdn.net/images/artist/0e2f0b185fa2eef93a490f40d13d269f/1000x1000-000000-80-0-0.jpg",
          "radio": true,
          "tracklist": "https://api.deezer.com/artist/7068771/top?limit=50",
          "position": 3,
          "type": "artist"
        },
        {
          "id": 4611283,
          "name": "Wesley Safadão",
          "link": "https://www.deezer.com/artist/4611283",
          "picture": "https://api.deezer.com/artist/4611283/image",
          "picture_small": "https://cdns-images.dzcdn.net/images/artist/d98c2a78c815e68712a0941c208bb7ba/56x56-000000-80-0-0.jpg",
          "picture_medium": "https://cdns-images.dzcdn.net/images/artist/d98c2a78c815e68712a0941c208bb7ba/250x250-000000-80-0-0.jpg",
          "picture_big": "https://cdns-images.dzcdn.net/images/artist/d98c2a78c815e68712a0941c208bb7ba/500x500-000000-80-0-0.jpg",
          "picture_xl": "https://cdns-images.dzcdn.net/images/artist/d98c2a78c815e68712a0941c208bb7ba/1000x1000-000000-80-0-0.jpg",
          "radio": true,
          "tracklist": "https://api.deezer.com/artist/4611283/top?limit=50",
          "position": 4,
          "type": "artist"
        },
        {
          "id": 5832280,
          "name": "Xand Avião",
          "link": "https://www.deezer.com/artist/5832280",
          "picture": "https://api.deezer.com/artist/5832280/image",
          "picture_small": "https://cdns-images.dzcdn.net/images/artist/606fbb66632064bd9138efb16c44ffed/56x56-000000-80-0-0.jpg",
          "picture_medium": "https://cdns-images.dzcdn.net/images/artist/606fbb66632064bd9138efb16c44ffed/250x250-000000-80-0-0.jpg",
          "picture_big": "https://cdns-images.dzcdn.net/images/artist/606fbb66632064bd9138efb16c44ffed/500x500-000000-80-0-0.jpg",
          "picture_xl": "https://cdns-images.dzcdn.net/images/artist/606fbb66632064bd9138efb16c44ffed/1000x1000-000000-80-0-0.jpg",
          "radio": true,
          "tracklist": "https://api.deezer.com/artist/5832280/top?limit=50",
          "position": 5,
          "type": "artist"
        },
        {
          "id": 5895828,
          "name": "Zé Neto & Cristiano",
          "link": "https://www.deezer.com/artist/5895828",
          "picture": "https://api.deezer.com/artist/5895828/image",
          "picture_small": "https://cdns-images.dzcdn.net/images/artist/100bc0927a9f152d2a9d85c169fe1901/56x56-000000-80-0-0.jpg",
          "picture_medium": "https://cdns-images.dzcdn.net/images/artist/100bc0927a9f152d2a9d85c169fe1901/250x250-000000-80-0-0.jpg",
          "picture_big": "https://cdns-images.dzcdn.net/images/artist/100bc0927a9f152d2a9d85c169fe1901/500x500-000000-80-0-0.jpg",
          "picture_xl": "https://cdns-images.dzcdn.net/images/artist/100bc0927a9f152d2a9d85c169fe1901/1000x1000-000000-80-0-0.jpg",
          "radio": true,
          "tracklist": "https://api.deezer.com/artist/5895828/top?limit=50",
          "position": 6,
          "type": "artist"
        },
        {
          "id": 84292982,
          "name": "Tarcísio do Acordeon",
          "link": "https://www.deezer.com/artist/84292982",
          "picture": "https://api.deezer.com/artist/84292982/image",
          "picture_small": "https://cdns-images.dzcdn.net/images/artist/94548d0fe20cecb5346e958d4aaed9e9/56x56-000000-80-0-0.jpg",
          "picture_medium": "https://cdns-images.dzcdn.net/images/artist/94548d0fe20cecb5346e958d4aaed9e9/250x250-000000-80-0-0.jpg",
          "picture_big": "https://cdns-images.dzcdn.net/images/artist/94548d0fe20cecb5346e958d4aaed9e9/500x500-000000-80-0-0.jpg",
          "picture_xl": "https://cdns-images.dzcdn.net/images/artist/94548d0fe20cecb5346e958d4aaed9e9/1000x1000-000000-80-0-0.jpg",
          "radio": true,
          "tracklist": "https://api.deezer.com/artist/84292982/top?limit=50",
          "position": 7,
          "type": "artist"
        },
        {
          "id": 54330242,
          "name": "Grupo Menos É Mais",
          "link": "https://www.deezer.com/artist/54330242",
          "picture": "https://api.deezer.com/artist/54330242/image",
          "picture_small": "https://cdns-images.dzcdn.net/images/artist/738abca3b6502aa093e5df1df1dad704/56x56-000000-80-0-0.jpg",
          "picture_medium": "https://cdns-images.dzcdn.net/images/artist/738abca3b6502aa093e5df1df1dad704/250x250-000000-80-0-0.jpg",
          "picture_big": "https://cdns-images.dzcdn.net/images/artist/738abca3b6502aa093e5df1df1dad704/500x500-000000-80-0-0.jpg",
          "picture_xl": "https://cdns-images.dzcdn.net/images/artist/738abca3b6502aa093e5df1df1dad704/1000x1000-000000-80-0-0.jpg",
          "radio": true,
          "tracklist": "https://api.deezer.com/artist/54330242/top?limit=50",
          "position": 8,
          "type": "artist"
        },
        {
          "id": 4876653,
          "name": "Henrique & Juliano",
          "link": "https://www.deezer.com/artist/4876653",
          "picture": "https://api.deezer.com/artist/4876653/image",
          "picture_small": "https://cdns-images.dzcdn.net/images/artist/439d0e35b1c2269ede25e3f30aae8f4c/56x56-000000-80-0-0.jpg",
          "picture_medium": "https://cdns-images.dzcdn.net/images/artist/439d0e35b1c2269ede25e3f30aae8f4c/250x250-000000-80-0-0.jpg",
          "picture_big": "https://cdns-images.dzcdn.net/images/artist/439d0e35b1c2269ede25e3f30aae8f4c/500x500-000000-80-0-0.jpg",
          "picture_xl": "https://cdns-images.dzcdn.net/images/artist/439d0e35b1c2269ede25e3f30aae8f4c/1000x1000-000000-80-0-0.jpg",
          "radio": true,
          "tracklist": "https://api.deezer.com/artist/4876653/top?limit=50",
          "position": 9,
          "type": "artist"
        },
        {
          "id": 68221232,
          "name": "Zé Vaqueiro",
          "link": "https://www.deezer.com/artist/68221232",
          "picture": "https://api.deezer.com/artist/68221232/image",
          "picture_small": "https://cdns-images.dzcdn.net/images/artist/d7a7aa96042e571ad1de55ddd20831bf/56x56-000000-80-0-0.jpg",
          "picture_medium": "https://cdns-images.dzcdn.net/images/artist/d7a7aa96042e571ad1de55ddd20831bf/250x250-000000-80-0-0.jpg",
          "picture_big": "https://cdns-images.dzcdn.net/images/artist/d7a7aa96042e571ad1de55ddd20831bf/500x500-000000-80-0-0.jpg",
          "picture_xl": "https://cdns-images.dzcdn.net/images/artist/d7a7aa96042e571ad1de55ddd20831bf/1000x1000-000000-80-0-0.jpg",
          "radio": true,
          "tracklist": "https://api.deezer.com/artist/68221232/top?limit=50",
          "position": 10,
          "type": "artist"
        }
      ],
      "total": 10
    },
    "playlists": {
      "data": [
        {
          "id": 5207214368,
          "title": "Top 50 Sertanejo",
          "public": true,
          "nb_tracks": 50,
          "link": "https://www.deezer.com/playlist/5207214368",
          "picture": "https://api.deezer.com/playlist/5207214368/image",
          "picture_small": "https://cdns-images.dzcdn.net/images/playlist/631596615588b853316bdc36f2ee6b4a/56x56-000000-80-0-0.jpg",
          "picture_medium": "https://cdns-images.dzcdn.net/images/playlist/631596615588b853316bdc36f2ee6b4a/250x250-000000-80-0-0.jpg",
          "picture_big": "https://cdns-images.dzcdn.net/images/playlist/631596615588b853316bdc36f2ee6b4a/500x500-000000-80-0-0.jpg",
          "picture_xl": "https://cdns-images.dzcdn.net/images/playlist/631596615588b853316bdc36f2ee6b4a/1000x1000-000000-80-0-0.jpg",
          "checksum": "9637e52fa8e9570f1ec8eb5820a35d9f",
          "tracklist": "https://api.deezer.com/playlist/5207214368/tracks",
          "creation_date": "2018-12-12 10:58:12",
          "md5_image": "631596615588b853316bdc36f2ee6b4a",
          "user": {
            "id": 2529028862,
            "name": "Polly - Deezer Editora de Sertanejo",
            "tracklist": "https://api.deezer.com/user/2529028862/flow",
            "type": "user"
          },
          "type": "playlist"
        },
        {
          "id": 1183242961,
          "title": "Funkadão",
          "public": true,
          "nb_tracks": 50,
          "link": "https://www.deezer.com/playlist/1183242961",
          "picture": "https://api.deezer.com/playlist/1183242961/image",
          "picture_small": "https://cdns-images.dzcdn.net/images/playlist/9a58685cb73b35be54c3b36ab6554e69/56x56-000000-80-0-0.jpg",
          "picture_medium": "https://cdns-images.dzcdn.net/images/playlist/9a58685cb73b35be54c3b36ab6554e69/250x250-000000-80-0-0.jpg",
          "picture_big": "https://cdns-images.dzcdn.net/images/playlist/9a58685cb73b35be54c3b36ab6554e69/500x500-000000-80-0-0.jpg",
          "picture_xl": "https://cdns-images.dzcdn.net/images/playlist/9a58685cb73b35be54c3b36ab6554e69/1000x1000-000000-80-0-0.jpg",
          "checksum": "8ae02db294d66cc9a2dc1ec351704b6e",
          "tracklist": "https://api.deezer.com/playlist/1183242961/tracks",
          "creation_date": "2015-03-19 15:49:47",
          "md5_image": "9a58685cb73b35be54c3b36ab6554e69",
          "user": {
            "id": 1178613186,
            "name": "Vithor - Editor Deezer Brasil",
            "tracklist": "https://api.deezer.com/user/1178613186/flow",
            "type": "user"
          },
          "type": "playlist"
        },
        {
          "id": 5230488882,
          "title": "Vem 2021!",
          "public": true,
          "nb_tracks": 50,
          "link": "https://www.deezer.com/playlist/5230488882",
          "picture": "https://api.deezer.com/playlist/5230488882/image",
          "picture_small": "https://cdns-images.dzcdn.net/images/playlist/279f60cd298f7b5f6563876e0d029d40/56x56-000000-80-0-0.jpg",
          "picture_medium": "https://cdns-images.dzcdn.net/images/playlist/279f60cd298f7b5f6563876e0d029d40/250x250-000000-80-0-0.jpg",
          "picture_big": "https://cdns-images.dzcdn.net/images/playlist/279f60cd298f7b5f6563876e0d029d40/500x500-000000-80-0-0.jpg",
          "picture_xl": "https://cdns-images.dzcdn.net/images/playlist/279f60cd298f7b5f6563876e0d029d40/1000x1000-000000-80-0-0.jpg",
          "checksum": "95733a140f90dffc96129ad04c8db1eb",
          "tracklist": "https://api.deezer.com/playlist/5230488882/tracks",
          "creation_date": "2018-12-18 16:29:09",
          "md5_image": "279f60cd298f7b5f6563876e0d029d40",
          "user": {
            "id": 303004553,
            "name": "Romar - Editor Deezer Brasil",
            "tracklist": "https://api.deezer.com/user/303004553/flow",
            "type": "user"
          },
          "type": "playlist"
        },
        {
          "id": 6742218764,
          "title": "Pisadinha & Paredão",
          "public": true,
          "nb_tracks": 50,
          "link": "https://www.deezer.com/playlist/6742218764",
          "picture": "https://api.deezer.com/playlist/6742218764/image",
          "picture_small": "https://cdns-images.dzcdn.net/images/playlist/f74dc2dae11aadc6812441a04981a4f9/56x56-000000-80-0-0.jpg",
          "picture_medium": "https://cdns-images.dzcdn.net/images/playlist/f74dc2dae11aadc6812441a04981a4f9/250x250-000000-80-0-0.jpg",
          "picture_big": "https://cdns-images.dzcdn.net/images/playlist/f74dc2dae11aadc6812441a04981a4f9/500x500-000000-80-0-0.jpg",
          "picture_xl": "https://cdns-images.dzcdn.net/images/playlist/f74dc2dae11aadc6812441a04981a4f9/1000x1000-000000-80-0-0.jpg",
          "checksum": "9d39ebe8166ffb29a626c88a3eca67bb",
          "tracklist": "https://api.deezer.com/playlist/6742218764/tracks",
          "creation_date": "2019-10-28 17:30:09",
          "md5_image": "f74dc2dae11aadc6812441a04981a4f9",
          "user": {
            "id": 2529028862,
            "name": "Polly - Deezer Editora de Sertanejo",
            "tracklist": "https://api.deezer.com/user/2529028862/flow",
            "type": "user"
          },
          "type": "playlist"
        },
        {
          "id": 1592591647,
          "title": "#hitou",
          "public": true,
          "nb_tracks": 60,
          "link": "https://www.deezer.com/playlist/1592591647",
          "picture": "https://api.deezer.com/playlist/1592591647/image",
          "picture_small": "https://cdns-images.dzcdn.net/images/playlist/f79e79bba3599f9cdee5d415f9aa0ebd/56x56-000000-80-0-0.jpg",
          "picture_medium": "https://cdns-images.dzcdn.net/images/playlist/f79e79bba3599f9cdee5d415f9aa0ebd/250x250-000000-80-0-0.jpg",
          "picture_big": "https://cdns-images.dzcdn.net/images/playlist/f79e79bba3599f9cdee5d415f9aa0ebd/500x500-000000-80-0-0.jpg",
          "picture_xl": "https://cdns-images.dzcdn.net/images/playlist/f79e79bba3599f9cdee5d415f9aa0ebd/1000x1000-000000-80-0-0.jpg",
          "checksum": "cea3638381d884f3e04edd54e514b17c",
          "tracklist": "https://api.deezer.com/playlist/1592591647/tracks",
          "creation_date": "2016-01-28 14:16:44",
          "md5_image": "f79e79bba3599f9cdee5d415f9aa0ebd",
          "user": {
            "id": 303004553,
            "name": "Romar - Editor Deezer Brasil",
            "tracklist": "https://api.deezer.com/user/303004553/flow",
            "type": "user"
          },
          "type": "playlist"
        },
        {
          "id": 1414852425,
          "title": "Estouradas do Forró",
          "public": true,
          "nb_tracks": 50,
          "link": "https://www.deezer.com/playlist/1414852425",
          "picture": "https://api.deezer.com/playlist/1414852425/image",
          "picture_small": "https://cdns-images.dzcdn.net/images/playlist/8a3706b078efc0e7229b7daa0f6a4105/56x56-000000-80-0-0.jpg",
          "picture_medium": "https://cdns-images.dzcdn.net/images/playlist/8a3706b078efc0e7229b7daa0f6a4105/250x250-000000-80-0-0.jpg",
          "picture_big": "https://cdns-images.dzcdn.net/images/playlist/8a3706b078efc0e7229b7daa0f6a4105/500x500-000000-80-0-0.jpg",
          "picture_xl": "https://cdns-images.dzcdn.net/images/playlist/8a3706b078efc0e7229b7daa0f6a4105/1000x1000-000000-80-0-0.jpg",
          "checksum": "2ce0736ade096e60ecd9be8907a62db2",
          "tracklist": "https://api.deezer.com/playlist/1414852425/tracks",
          "creation_date": "2015-10-15 15:38:18",
          "md5_image": "8a3706b078efc0e7229b7daa0f6a4105",
          "user": {
            "id": 2529028862,
            "name": "Polly - Deezer Editora de Sertanejo",
            "tracklist": "https://api.deezer.com/user/2529028862/flow",
            "type": "user"
          },
          "type": "playlist"
        },
        {
          "id": 1082925547,
          "title": "Vem pro Sertanejo",
          "public": true,
          "nb_tracks": 50,
          "link": "https://www.deezer.com/playlist/1082925547",
          "picture": "https://api.deezer.com/playlist/1082925547/image",
          "picture_small": "https://cdns-images.dzcdn.net/images/playlist/dda492e895a883ac02b4be63391f304b/56x56-000000-80-0-0.jpg",
          "picture_medium": "https://cdns-images.dzcdn.net/images/playlist/dda492e895a883ac02b4be63391f304b/250x250-000000-80-0-0.jpg",
          "picture_big": "https://cdns-images.dzcdn.net/images/playlist/dda492e895a883ac02b4be63391f304b/500x500-000000-80-0-0.jpg",
          "picture_xl": "https://cdns-images.dzcdn.net/images/playlist/dda492e895a883ac02b4be63391f304b/1000x1000-000000-80-0-0.jpg",
          "checksum": "59e09aac1f54232689d47b3f02fe8add",
          "tracklist": "https://api.deezer.com/playlist/1082925547/tracks",
          "creation_date": "2014-12-18 15:04:03",
          "md5_image": "dda492e895a883ac02b4be63391f304b",
          "user": {
            "id": 2529028862,
            "name": "Polly - Deezer Editora de Sertanejo",
            "tracklist": "https://api.deezer.com/user/2529028862/flow",
            "type": "user"
          },
          "type": "playlist"
        },
        {
          "id": 973678543,
          "title": "Explosão Brasil",
          "public": true,
          "nb_tracks": 50,
          "link": "https://www.deezer.com/playlist/973678543",
          "picture": "https://api.deezer.com/playlist/973678543/image",
          "picture_small": "https://cdns-images.dzcdn.net/images/playlist/ec5ee7b26d365588aacd7fd11aa28050/56x56-000000-80-0-0.jpg",
          "picture_medium": "https://cdns-images.dzcdn.net/images/playlist/ec5ee7b26d365588aacd7fd11aa28050/250x250-000000-80-0-0.jpg",
          "picture_big": "https://cdns-images.dzcdn.net/images/playlist/ec5ee7b26d365588aacd7fd11aa28050/500x500-000000-80-0-0.jpg",
          "picture_xl": "https://cdns-images.dzcdn.net/images/playlist/ec5ee7b26d365588aacd7fd11aa28050/1000x1000-000000-80-0-0.jpg",
          "checksum": "41a480f46aee62d758e14241372ebc61",
          "tracklist": "https://api.deezer.com/playlist/973678543/tracks",
          "creation_date": "2014-09-01 12:04:38",
          "md5_image": "ec5ee7b26d365588aacd7fd11aa28050",
          "user": {
            "id": 303004553,
            "name": "Romar - Editor Deezer Brasil",
            "tracklist": "https://api.deezer.com/user/303004553/flow",
            "type": "user"
          },
          "type": "playlist"
        },
        {
          "id": 8422904922,
          "title": "O Melhor do Sertanejo 2020",
          "public": true,
          "nb_tracks": 50,
          "link": "https://www.deezer.com/playlist/8422904922",
          "picture": "https://api.deezer.com/playlist/8422904922/image",
          "picture_small": "https://cdns-images.dzcdn.net/images/playlist/46b547222ce6b45da3473ad18a4d41ce/56x56-000000-80-0-0.jpg",
          "picture_medium": "https://cdns-images.dzcdn.net/images/playlist/46b547222ce6b45da3473ad18a4d41ce/250x250-000000-80-0-0.jpg",
          "picture_big": "https://cdns-images.dzcdn.net/images/playlist/46b547222ce6b45da3473ad18a4d41ce/500x500-000000-80-0-0.jpg",
          "picture_xl": "https://cdns-images.dzcdn.net/images/playlist/46b547222ce6b45da3473ad18a4d41ce/1000x1000-000000-80-0-0.jpg",
          "checksum": "661bb1d9be98cce6f0929e0725c88a71",
          "tracklist": "https://api.deezer.com/playlist/8422904922/tracks",
          "creation_date": "2020-11-30 09:22:16",
          "md5_image": "46b547222ce6b45da3473ad18a4d41ce",
          "user": {
            "id": 4036709482,
            "name": "Deezer Best Of",
            "tracklist": "https://api.deezer.com/user/4036709482/flow",
            "type": "user"
          },
          "type": "playlist"
        },
        {
          "id": 1336751325,
          "title": "Festa Sertaneja",
          "public": true,
          "nb_tracks": 50,
          "link": "https://www.deezer.com/playlist/1336751325",
          "picture": "https://api.deezer.com/playlist/1336751325/image",
          "picture_small": "https://cdns-images.dzcdn.net/images/playlist/90e6c1078de8b360e71f6d79d3638c4c/56x56-000000-80-0-0.jpg",
          "picture_medium": "https://cdns-images.dzcdn.net/images/playlist/90e6c1078de8b360e71f6d79d3638c4c/250x250-000000-80-0-0.jpg",
          "picture_big": "https://cdns-images.dzcdn.net/images/playlist/90e6c1078de8b360e71f6d79d3638c4c/500x500-000000-80-0-0.jpg",
          "picture_xl": "https://cdns-images.dzcdn.net/images/playlist/90e6c1078de8b360e71f6d79d3638c4c/1000x1000-000000-80-0-0.jpg",
          "checksum": "7f4f7ad9f9775667da3fe552feb462b8",
          "tracklist": "https://api.deezer.com/playlist/1336751325/tracks",
          "creation_date": "2015-08-12 11:00:57",
          "md5_image": "90e6c1078de8b360e71f6d79d3638c4c",
          "user": {
            "id": 2529028862,
            "name": "Polly - Deezer Editora de Sertanejo",
            "tracklist": "https://api.deezer.com/user/2529028862/flow",
            "type": "user"
          },
          "type": "playlist"
        }
      ],
      "total": 10
    },
    "podcasts": {
      "data": [
        {
          "id": 2083082,
          "title": "Céu da Semana Especial: Previsões/2021",
          "description": "Como os astros influenciarão sua vida em 2021? Confira esta seleção especial do Céu da Semana que apresenta as previsões para todos os signos do zodíaco.",
          "available": true,
          "fans": 1718,
          "link": "https://www.deezer.com/show/2083082",
          "share": "https://www.deezer.com/show/2083082?utm_source=deezer&utm_content=show-2083082&utm_term=0_1609621999&utm_medium=web",
          "picture": "https://cdns-images.dzcdn.net/images/talk/c8e522932eeb949a744004d42bce30c7/180x180-000000-80-0-0.jpg",
          "picture_small": "https://cdns-images.dzcdn.net/images/talk/c8e522932eeb949a744004d42bce30c7/56x56-000000-80-0-0.jpg",
          "picture_medium": "https://cdns-images.dzcdn.net/images/talk/c8e522932eeb949a744004d42bce30c7/250x250-000000-80-0-0.jpg",
          "picture_big": "https://cdns-images.dzcdn.net/images/talk/c8e522932eeb949a744004d42bce30c7/500x500-000000-80-0-0.jpg",
          "picture_xl": "https://cdns-images.dzcdn.net/images/talk/c8e522932eeb949a744004d42bce30c7/1000x1000-000000-80-0-0.jpg",
          "type": "podcast"
        },
        {
          "id": 406562,
          "title": "Flow Podcast",
          "description": "Flow Podcast acontece todo dia de segunda à sexta, normalmente às 20h, AO VIVO simultaneamente no Youtube, Twitch e Facebook!",
          "available": true,
          "fans": 25406,
          "link": "https://www.deezer.com/show/406562",
          "share": "https://www.deezer.com/show/406562?utm_source=deezer&utm_content=show-406562&utm_term=0_1609621999&utm_medium=web",
          "picture": "https://cdns-images.dzcdn.net/images/talk/5713f8131d34241b1e1429d1a2bedad8/180x180-000000-80-0-0.jpg",
          "picture_small": "https://cdns-images.dzcdn.net/images/talk/5713f8131d34241b1e1429d1a2bedad8/56x56-000000-80-0-0.jpg",
          "picture_medium": "https://cdns-images.dzcdn.net/images/talk/5713f8131d34241b1e1429d1a2bedad8/250x250-000000-80-0-0.jpg",
          "picture_big": "https://cdns-images.dzcdn.net/images/talk/5713f8131d34241b1e1429d1a2bedad8/500x500-000000-80-0-0.jpg",
          "picture_xl": "https://cdns-images.dzcdn.net/images/talk/5713f8131d34241b1e1429d1a2bedad8/1000x1000-000000-80-0-0.jpg",
          "type": "podcast"
        },
        {
          "id": 2092492,
          "title": "Universo Sertanejo",
          "description": "Uma produção original da Deezer, o Universo Sertanejo é um um podcast especial com o jornalista André Piunti em um papo entre amigos com nomes de sucesso da música sertaneja.",
          "available": true,
          "fans": 370,
          "link": "https://www.deezer.com/show/2092492",
          "share": "https://www.deezer.com/show/2092492?utm_source=deezer&utm_content=show-2092492&utm_term=0_1609621999&utm_medium=web",
          "picture": "https://cdns-images.dzcdn.net/images/talk/af8d88668f28fbae89a0b2612856568c/180x180-000000-80-0-0.jpg",
          "picture_small": "https://cdns-images.dzcdn.net/images/talk/af8d88668f28fbae89a0b2612856568c/56x56-000000-80-0-0.jpg",
          "picture_medium": "https://cdns-images.dzcdn.net/images/talk/af8d88668f28fbae89a0b2612856568c/250x250-000000-80-0-0.jpg",
          "picture_big": "https://cdns-images.dzcdn.net/images/talk/af8d88668f28fbae89a0b2612856568c/500x500-000000-80-0-0.jpg",
          "picture_xl": "https://cdns-images.dzcdn.net/images/talk/af8d88668f28fbae89a0b2612856568c/1000x1000-000000-80-0-0.jpg",
          "type": "podcast"
        },
        {
          "id": 45529,
          "title": "NerdCast",
          "description": "O mundo vira piada no Jovem Nerd",
          "available": true,
          "fans": 51152,
          "link": "https://www.deezer.com/show/45529",
          "share": "https://www.deezer.com/show/45529?utm_source=deezer&utm_content=show-45529&utm_term=0_1609621999&utm_medium=web",
          "picture": "https://cdns-images.dzcdn.net/images/talk/83c7cc77b89bbd7f555766b49060d7c7/180x180-000000-80-0-0.jpg",
          "picture_small": "https://cdns-images.dzcdn.net/images/talk/83c7cc77b89bbd7f555766b49060d7c7/56x56-000000-80-0-0.jpg",
          "picture_medium": "https://cdns-images.dzcdn.net/images/talk/83c7cc77b89bbd7f555766b49060d7c7/250x250-000000-80-0-0.jpg",
          "picture_big": "https://cdns-images.dzcdn.net/images/talk/83c7cc77b89bbd7f555766b49060d7c7/500x500-000000-80-0-0.jpg",
          "picture_xl": "https://cdns-images.dzcdn.net/images/talk/83c7cc77b89bbd7f555766b49060d7c7/1000x1000-000000-80-0-0.jpg",
          "type": "podcast"
        },
        {
          "id": 1788472,
          "title": "Podpah",
          "description": "O podcast mais zika da internet",
          "available": true,
          "fans": 2737,
          "link": "https://www.deezer.com/show/1788472",
          "share": "https://www.deezer.com/show/1788472?utm_source=deezer&utm_content=show-1788472&utm_term=0_1609621999&utm_medium=web",
          "picture": "https://cdns-images.dzcdn.net/images/talk/113205167100781bdb33143668f7258c/180x180-000000-80-0-0.jpg",
          "picture_small": "https://cdns-images.dzcdn.net/images/talk/113205167100781bdb33143668f7258c/56x56-000000-80-0-0.jpg",
          "picture_medium": "https://cdns-images.dzcdn.net/images/talk/113205167100781bdb33143668f7258c/250x250-000000-80-0-0.jpg",
          "picture_big": "https://cdns-images.dzcdn.net/images/talk/113205167100781bdb33143668f7258c/500x500-000000-80-0-0.jpg",
          "picture_xl": "https://cdns-images.dzcdn.net/images/talk/113205167100781bdb33143668f7258c/1000x1000-000000-80-0-0.jpg",
          "type": "podcast"
        },
        {
          "id": 62292,
          "title": "Céu da Semana com Titi Vidal",
          "description": "Toda semana novos episódios com as previsões para todos os signos.\r\n\r\nCéu da Semana com Titi Vidal é o podcast original da Deezer para os amantes do zodíaco. A cada episódio o podcast apresenta as previsões astrológicas para a semana. Céu da Semana é apresentado por Titi Vidal, astróloga, taróloga, consteladora familiar e terapeuta. Escute e confira o que os astros reservam para você.",
          "available": true,
          "fans": 29159,
          "link": "https://www.deezer.com/show/62292",
          "share": "https://www.deezer.com/show/62292?utm_source=deezer&utm_content=show-62292&utm_term=0_1609621999&utm_medium=web",
          "picture": "https://cdns-images.dzcdn.net/images/talk/a4fd614ef8a6879d1bc88a3d5739437e/180x180-000000-80-0-0.jpg",
          "picture_small": "https://cdns-images.dzcdn.net/images/talk/a4fd614ef8a6879d1bc88a3d5739437e/56x56-000000-80-0-0.jpg",
          "picture_medium": "https://cdns-images.dzcdn.net/images/talk/a4fd614ef8a6879d1bc88a3d5739437e/250x250-000000-80-0-0.jpg",
          "picture_big": "https://cdns-images.dzcdn.net/images/talk/a4fd614ef8a6879d1bc88a3d5739437e/500x500-000000-80-0-0.jpg",
          "picture_xl": "https://cdns-images.dzcdn.net/images/talk/a4fd614ef8a6879d1bc88a3d5739437e/1000x1000-000000-80-0-0.jpg",
          "type": "podcast"
        },
        {
          "id": 753372,
          "title": "Modus Operandi",
          "description": "Podcast de true crime feito por Carol Moreira e Mabê.",
          "available": true,
          "fans": 10512,
          "link": "https://www.deezer.com/show/753372",
          "share": "https://www.deezer.com/show/753372?utm_source=deezer&utm_content=show-753372&utm_term=0_1609621999&utm_medium=web",
          "picture": "https://cdns-images.dzcdn.net/images/talk/a23a8625cf0c3a322c787f91e8998df0/180x180-000000-80-0-0.jpg",
          "picture_small": "https://cdns-images.dzcdn.net/images/talk/a23a8625cf0c3a322c787f91e8998df0/56x56-000000-80-0-0.jpg",
          "picture_medium": "https://cdns-images.dzcdn.net/images/talk/a23a8625cf0c3a322c787f91e8998df0/250x250-000000-80-0-0.jpg",
          "picture_big": "https://cdns-images.dzcdn.net/images/talk/a23a8625cf0c3a322c787f91e8998df0/500x500-000000-80-0-0.jpg",
          "picture_xl": "https://cdns-images.dzcdn.net/images/talk/a23a8625cf0c3a322c787f91e8998df0/1000x1000-000000-80-0-0.jpg",
          "type": "podcast"
        },
        {
          "id": 57199,
          "title": "Autoconsciente",
          "description": "Este é um podcast que entende você, para você entender melhor sua mente e emoções. Para ter uma relação mais leve consigo mesmo, baixando o tom da autocobrança e da autocrítica que ecoam na cabeça. Para que possa encontrar, dentro de você, a paz que está tão difícil de encontrar no mundo.   Autoconsciente é um bom lugar para se estar nestes nossos tempos conturbados. Seus episódios retratam situações que todos nós vivemos, com uma abordagem esclarecedora, acolhedora, que reenergiza. Mais do que um conteúdo, você encontra aqui uma experiência pacificadora.   Por Regina Giannetti - No Instragram @regina.giannetti e @vocemaiscentrado",
          "available": true,
          "fans": 29036,
          "link": "https://www.deezer.com/show/57199",
          "share": "https://www.deezer.com/show/57199?utm_source=deezer&utm_content=show-57199&utm_term=0_1609621999&utm_medium=web",
          "picture": "https://cdns-images.dzcdn.net/images/talk/70add5b7743e985d636ee13cad382720/180x180-000000-80-0-0.jpg",
          "picture_small": "https://cdns-images.dzcdn.net/images/talk/70add5b7743e985d636ee13cad382720/56x56-000000-80-0-0.jpg",
          "picture_medium": "https://cdns-images.dzcdn.net/images/talk/70add5b7743e985d636ee13cad382720/250x250-000000-80-0-0.jpg",
          "picture_big": "https://cdns-images.dzcdn.net/images/talk/70add5b7743e985d636ee13cad382720/500x500-000000-80-0-0.jpg",
          "picture_xl": "https://cdns-images.dzcdn.net/images/talk/70add5b7743e985d636ee13cad382720/1000x1000-000000-80-0-0.jpg",
          "type": "podcast"
        },
        {
          "id": 69491,
          "title": "Inglês do Zero",
          "description": "O Inglês do Zero Podcast é destinado às pessoas que têm dificuldade em encontrar bons materiais online para aprender inglês sozinhos.  Aqui você encontrará o passo a passo do estudo auto-didata de um jeito descontraído e com uma metodologia que te ajudará a aprender definitivamente o idioma.  Apresentação: Jader Lelis (Teacher Jay).",
          "available": true,
          "fans": 59608,
          "link": "https://www.deezer.com/show/69491",
          "share": "https://www.deezer.com/show/69491?utm_source=deezer&utm_content=show-69491&utm_term=0_1609621999&utm_medium=web",
          "picture": "https://cdns-images.dzcdn.net/images/talk/5a1b1decdb80fb2bad26804dffae151e/180x180-000000-80-0-0.jpg",
          "picture_small": "https://cdns-images.dzcdn.net/images/talk/5a1b1decdb80fb2bad26804dffae151e/56x56-000000-80-0-0.jpg",
          "picture_medium": "https://cdns-images.dzcdn.net/images/talk/5a1b1decdb80fb2bad26804dffae151e/250x250-000000-80-0-0.jpg",
          "picture_big": "https://cdns-images.dzcdn.net/images/talk/5a1b1decdb80fb2bad26804dffae151e/500x500-000000-80-0-0.jpg",
          "picture_xl": "https://cdns-images.dzcdn.net/images/talk/5a1b1decdb80fb2bad26804dffae151e/1000x1000-000000-80-0-0.jpg",
          "type": "podcast"
        },
        {
          "id": 1950252,
          "title": "Não Inviabilize",
          "description": "O canal Não Inviabilize é um espaço de contos e crônicas, um laboratório de histórias reais. Histórias de temas variados contadas semanalmente. Quadros do canal: Amor Nas Redes - histórias de amor e afeto com finais felizes ou tristes; Picolé de Limão - histórias do cotidiano, ciladas, trapaças, muita história revoltante; Luz Acesa - histórias de terror, suspense e mistério; Ficção da Realidade - histórias ficcionais interativas; Mico Meu - histórias engraçadas; Patada - histórias sobre cães e gatos; Alarme - histórias (gatilho) com desfecho favorável à vitima. E-mail: naoinviabilize@gmail.com",
          "available": true,
          "fans": 508,
          "link": "https://www.deezer.com/show/1950252",
          "share": "https://www.deezer.com/show/1950252?utm_source=deezer&utm_content=show-1950252&utm_term=0_1609621999&utm_medium=web",
          "picture": "https://cdns-images.dzcdn.net/images/talk/cec556af96a644ea50d6bfc2d3276bd5/180x180-000000-80-0-0.jpg",
          "picture_small": "https://cdns-images.dzcdn.net/images/talk/cec556af96a644ea50d6bfc2d3276bd5/56x56-000000-80-0-0.jpg",
          "picture_medium": "https://cdns-images.dzcdn.net/images/talk/cec556af96a644ea50d6bfc2d3276bd5/250x250-000000-80-0-0.jpg",
          "picture_big": "https://cdns-images.dzcdn.net/images/talk/cec556af96a644ea50d6bfc2d3276bd5/500x500-000000-80-0-0.jpg",
          "picture_xl": "https://cdns-images.dzcdn.net/images/talk/cec556af96a644ea50d6bfc2d3276bd5/1000x1000-000000-80-0-0.jpg",
          "type": "podcast"
        }
      ],
      "total": 10
    }
  }